w2w/__init__.py
w2w/w2w.py
w2w/resources/LCZ_UCP_lookup.csv
w2w/resources/__init__.py
w2w-0.6.0.dist-info/LICENSE
w2w-0.6.0.dist-info/METADATA
w2w-0.6.0.dist-info/WHEEL
w2w-0.6.0.dist-info/entry_points.txt
w2w-0.6.0.dist-info/top_level.txt
w2w-0.6.0.dist-info/RECORD
