Metadata-Version: 2.1
Name: w2w
Version: 0.6.0
Summary: A python tool that ingests WUDAPT's Local Climate Zone information into WRF.
Home-page: https://github.com/matthiasdemuzere/w2w
Author: Matthias Demuzere, Daniel Argueso, Andrea Zonato, Jonas Kittner
Author-email: mdemuzere@gmail.com
License: MIT
Classifier: License :: OSI Approved :: MIT License
Classifier: Programming Language :: Python :: 3
Classifier: Programming Language :: Python :: 3 :: Only
Classifier: Programming Language :: Python :: Implementation :: CPython
Requires-Python: >=3.8
License-File: LICENSE
Requires-Dist: ecmwflibs
Requires-Dist: h5netcdf
Requires-Dist: netCDF4
Requires-Dist: numpy>=1.21
Requires-Dist: pandas
Requires-Dist: rasterio<1.4.0,>=1.1.6
Requires-Dist: rioxarray
Requires-Dist: scipy
Requires-Dist: tqdm
Requires-Dist: xarray>=0.17.0
Requires-Dist: importlib-metadata; python_version < "3.9"
Requires-Dist: importlib-resources; python_version < "3.9"
